gabbar/__init__.py
gabbar/helpers/real_changesets.js
gabbar/scripts/__init__.py
gabbar/scripts/cli.py
gabbar/trained/model.pkl
gabbar/trained/scaler.pkl
gabbar-0.5.1.dist-info/DESCRIPTION.rst
gabbar-0.5.1.dist-info/METADATA
gabbar-0.5.1.dist-info/RECORD
gabbar-0.5.1.dist-info/WHEEL
gabbar-0.5.1.dist-info/entry_points.txt
gabbar-0.5.1.dist-info/metadata.json
gabbar-0.5.1.dist-info/top_level.txt
