Metadata-Version: 2.0
Name: gabbar
Version: 0.5.1
Summary: Guarding OpenStreetMap from invalid or suspicious edits!
Home-page: https://github.com/mapbox/gabbar
Author: Mapbox
Author-email: team@mapbox.com
License: MIT
Keywords: osm
Platform: UNKNOWN
Classifier: Development Status :: 3 - Alpha
Classifier: Intended Audience :: Developers
Classifier: Programming Language :: Python :: 3.6
Requires-Dist: click
Requires-Dist: numpy
Requires-Dist: scikit-learn[alldeps]
Requires-Dist: scipy
Provides-Extra: test
Requires-Dist: pandas; extra == 'test'
Requires-Dist: pytest; extra == 'test'
Requires-Dist: requests; extra == 'test'
Requires-Dist: twine; extra == 'test'
